cloudcomponents/cdk_stripe_webhook/__init__.py
cloudcomponents/cdk_stripe_webhook/py.typed
cloudcomponents/cdk_stripe_webhook/_jsii/__init__.py
cloudcomponents/cdk_stripe_webhook/_jsii/cdk-stripe-webhook@2.4.0.jsii.tgz
cloudcomponents.cdk_stripe_webhook-2.4.0.dist-info/LICENSE
cloudcomponents.cdk_stripe_webhook-2.4.0.dist-info/METADATA
cloudcomponents.cdk_stripe_webhook-2.4.0.dist-info/WHEEL
cloudcomponents.cdk_stripe_webhook-2.4.0.dist-info/top_level.txt
cloudcomponents.cdk_stripe_webhook-2.4.0.dist-info/RECORD
