Metadata-Version: 2.1
Name: cloudcomponents.cdk-stripe-webhook
Version: 2.4.0
Summary: Create, update and delete stripe webhooks with your app deployment
Home-page: https://github.com/cloudcomponents/cdk-constructs
Author: hupe1980
License: MIT
Project-URL: Source, https://github.com/cloudcomponents/cdk-constructs.git
Classifier: Intended Audience :: Developers
Classifier: Operating System :: OS Independent
Classifier: Programming Language :: JavaScript
Classifier: Programming Language :: Python :: 3 :: Only
Classifier: Programming Language :: Python :: 3.8
Classifier: Programming Language :: Python :: 3.9
Classifier: Programming Language :: Python :: 3.10
Classifier: Programming Language :: Python :: 3.11
Classifier: Typing :: Typed
Classifier: License :: OSI Approved
Requires-Python: ~=3.8
License-File: LICENSE
Requires-Dist: aws-cdk-lib <3.0.0,>=2.141.0
Requires-Dist: cloudcomponents.cdk-secret-key <3.0.0,>=2.2.0
Requires-Dist: constructs <11.0.0,>=10.3.0
Requires-Dist: jsii <2.0.0,>=1.95.0
Requires-Dist: publication >=0.0.3
Requires-Dist: typeguard ~=2.13.3
